{
  "browser": "chrome-unstable",
  "version": {
    "from": "116.0.5829.0",
    "to": "116.0.5845.4"
  },
  "browserApis": {
    "added": [
      "DocumentPictureInPicture",
      "DocumentPictureInPicture.prototype",
      "DocumentPictureInPicture.prototype.onenter",
      "DocumentPictureInPicture.prototype.requestWindow",
      "DocumentPictureInPicture.prototype.window",
      "DocumentPictureInPictureEvent",
      "DocumentPictureInPictureEvent.prototype",
      "DocumentPictureInPictureEvent.prototype.window",
      "IdentityProvider",
      "IdentityProvider.getUserInfo",
      "IdentityProvider.prototype",
      "documentPictureInPicture"
    ],
    "removed": []
  }
}